spotify_py_sdk/__init__.py
spotify_py_sdk/auth/__init__.py
spotify_py_sdk/auth/access_token_manager.py
spotify_py_sdk/endpoints/__init__.py
spotify_py_sdk/endpoints/albums.py
spotify_py_sdk/endpoints/artists.py
spotify_py_sdk/endpoints/audiobooks.py
spotify_py_sdk/endpoints/browse.py
spotify_py_sdk/endpoints/chapters.py
spotify_py_sdk/endpoints/current_user.py
spotify_py_sdk/endpoints/endpoints_base.py
spotify_py_sdk/endpoints/episodes.py
spotify_py_sdk/endpoints/markets.py
spotify_py_sdk/endpoints/player.py
spotify_py_sdk/endpoints/playlists.py
spotify_py_sdk/endpoints/recommendations.py
spotify_py_sdk/endpoints/search.py
spotify_py_sdk/endpoints/shows.py
spotify_py_sdk/endpoints/tracks.py
spotify_py_sdk/endpoints/users.py
spotify_py_sdk/spotify_api.py
spotify_py_sdk/types.py
spotify_py_sdk-0.1.2.dist-info/LICENSE
spotify_py_sdk-0.1.2.dist-info/METADATA
spotify_py_sdk-0.1.2.dist-info/WHEEL
spotify_py_sdk-0.1.2.dist-info/RECORD
