Metadata-Version: 2.1
Name: spotify_py_sdk
Version: 0.1.2
Summary: Python SDK for Spotify
Author: Ananya Nayak
Author-email: ananyanayak102@gmail.com
Requires-Python: >=3.9,<4.0
Classifier: Programming Language :: Python :: 3
Classifier: Programming Language :: Python :: 3.9
Classifier: Programming Language :: Python :: 3.10
Classifier: Programming Language :: Python :: 3.11
Classifier: Programming Language :: Python :: 3.12
Requires-Dist: requests (>=2.31.0,<3.0.0)
